dynabyte/__init__.py
dynabyte/core.py
dynabyte/operations.py
dynabyte/utils.py
dynabyte/version.py
dynabyte-2.2.1.dist-info/LICENSE
dynabyte-2.2.1.dist-info/METADATA
dynabyte-2.2.1.dist-info/WHEEL
dynabyte-2.2.1.dist-info/top_level.txt
dynabyte-2.2.1.dist-info/RECORD
