Metadata-Version: 2.1
Name: dynabyte
Version: 2.2.1
Summary: Byte manipulation module for files and arrays
Home-page: https://github.com/LLCZ00/Dynabyte
Author: LLCZ00
License: Apache 2.0
Keywords: malware analysis obfuscation strings files
Classifier: Development Status :: 5 - Production/Stable
Classifier: Intended Audience :: Information Technology
Classifier: Intended Audience :: Developers
Classifier: License :: OSI Approved :: Apache Software License
Classifier: Natural Language :: English
Classifier: Programming Language :: Python :: 3
Classifier: Operating System :: OS Independent
Classifier: Topic :: Security
Classifier: Topic :: Security :: Cryptography
Classifier: Topic :: Utilities
Requires-Python: >=3.8
License-File: LICENSE
Requires-Dist: pycryptodome
